aiohttp_apispec_plugin/__init__.py
aiohttp_apispec_plugin/aiohttp_plugin.py
aiohttp_apispec_plugin/utils.py
aiohttp_apispec_plugin/version.py
aiohttp_apispec_plugin-0.2.dist-info/LICENSE
aiohttp_apispec_plugin-0.2.dist-info/METADATA
aiohttp_apispec_plugin-0.2.dist-info/WHEEL
aiohttp_apispec_plugin-0.2.dist-info/top_level.txt
aiohttp_apispec_plugin-0.2.dist-info/RECORD
