Metadata-Version: 2.1
Name: aiohttp-apispec-plugin
Version: 0.2
Summary: APISpec plugin for aiohttp
Home-page: https://github.com/ckkz-it/aiohttp-apispec-plugin
Author: Andrey Laguta
Author-email: cirkus.kz@gmail.com
License: MIT
Keywords: aiohttp apispec aiohttp_apispec_plugin
Platform: UNKNOWN
Classifier: Development Status :: 5 - Production/Stable
Classifier: Environment :: Web Environment
Classifier: Framework :: AsyncIO
Classifier: Intended Audience :: Developers
Classifier: Operating System :: OS Independent
Classifier: Programming Language :: Python :: 3.6
Classifier: Programming Language :: Python :: 3.7
Classifier: Programming Language :: Python :: 3.8
Classifier: Topic :: Internet :: WWW/HTTP
Classifier: Topic :: Documentation
Classifier: License :: OSI Approved :: MIT License
Requires-Python: >=3.6
Requires-Dist: aiohttp
Requires-Dist: apispec
